README.txt
setup.cfg
setup.py
collective/__init__.py
collective.contentrules.template.egg-info/PKG-INFO
collective.contentrules.template.egg-info/SOURCES.txt
collective.contentrules.template.egg-info/dependency_links.txt
collective.contentrules.template.egg-info/entry_points.txt
collective.contentrules.template.egg-info/namespace_packages.txt
collective.contentrules.template.egg-info/not-zip-safe
collective.contentrules.template.egg-info/requires.txt
collective.contentrules.template.egg-info/top_level.txt
collective/contentrules/__init__.py
collective/contentrules/template/__init__.py
collective/contentrules/template/action.py
collective/contentrules/template/configure.zcml
collective/contentrules/template/tests.py
docs/HISTORY.txt
docs/INSTALL.txt
docs/LICENSE.GPL
docs/LICENSE.txt