Metadata-Version: 1.0
Name: collective.contentrules.template
Version: 1.0
Summary: A Plone content rule for creating content based on templates
Home-page: http://pypi.python.org/pypi/collective.contentrules.template
Author: Luciano Pacheco
Author-email: lucmult@gmail.com
License: GPL
Keywords: plone content rules template
Platform: UNKNOWN
Classifier: Framework :: Plone
Classifier: Programming Language :: Python
Classifier: Topic :: Software Development :: Libraries :: Python Modules
